cognite_jupyterlab_metrics/__init__.py
cognite_jupyterlab_metrics/_version.py
cognite_jupyterlab_metrics-0.1.0.data/data/share/jupyter/labextensions/cognite_jupyterlab_metrics/build_log.json
cognite_jupyterlab_metrics-0.1.0.data/data/share/jupyter/labextensions/cognite_jupyterlab_metrics/package.json
cognite_jupyterlab_metrics-0.1.0.data/data/share/jupyter/labextensions/cognite_jupyterlab_metrics/schemas/cognite_jupyterlab_metrics/package.json.orig
cognite_jupyterlab_metrics-0.1.0.data/data/share/jupyter/labextensions/cognite_jupyterlab_metrics/schemas/cognite_jupyterlab_metrics/plugin.json
cognite_jupyterlab_metrics-0.1.0.data/data/share/jupyter/labextensions/cognite_jupyterlab_metrics/static/lib_index_js.f1f6a0d009883b94d4a5.js
cognite_jupyterlab_metrics-0.1.0.data/data/share/jupyter/labextensions/cognite_jupyterlab_metrics/static/lib_index_js.f1f6a0d009883b94d4a5.js.map
cognite_jupyterlab_metrics-0.1.0.data/data/share/jupyter/labextensions/cognite_jupyterlab_metrics/static/remoteEntry.223efbf3dfd40fb5c832.js
cognite_jupyterlab_metrics-0.1.0.data/data/share/jupyter/labextensions/cognite_jupyterlab_metrics/static/remoteEntry.223efbf3dfd40fb5c832.js.map
cognite_jupyterlab_metrics-0.1.0.data/data/share/jupyter/labextensions/cognite_jupyterlab_metrics/static/style.js
cognite_jupyterlab_metrics-0.1.0.data/data/share/jupyter/labextensions/cognite_jupyterlab_metrics/static/style_index_js.7e35ed8317794ee38ec0.js
cognite_jupyterlab_metrics-0.1.0.data/data/share/jupyter/labextensions/cognite_jupyterlab_metrics/static/style_index_js.7e35ed8317794ee38ec0.js.map
cognite_jupyterlab_metrics-0.1.0.data/data/share/jupyter/labextensions/cognite_jupyterlab_metrics/install.json
cognite_jupyterlab_metrics-0.1.0.dist-info/METADATA
cognite_jupyterlab_metrics-0.1.0.dist-info/WHEEL
cognite_jupyterlab_metrics-0.1.0.dist-info/licenses/LICENSE
cognite_jupyterlab_metrics-0.1.0.dist-info/RECORD
