Metadata-Version: 2.1
Name: cognite_jupyterlab_metrics
Version: 0.1.0
Summary: A JupyterLab extension for gathering notebook metrics.
Project-URL: Homepage, https://github.com/cognitedata/cognite-jupyterlab-metrics
Project-URL: Bug Tracker, https://github.com/cognitedata/cognite-jupyterlab-metrics/issues
Project-URL: Repository, https://github.com/cognitedata/cognite-jupyterlab-metrics.git
Author-email: Anders Hafreager <anders.hafreager@cognite.com>
License: BSD 3-Clause License
License-File: LICENSE
Classifier: Framework :: Jupyter
Classifier: Framework :: Jupyter :: JupyterLab
Classifier: Framework :: Jupyter :: JupyterLab :: 3
Classifier: Framework :: Jupyter :: JupyterLab :: Extensions
Classifier: Framework :: Jupyter :: JupyterLab :: Extensions :: Prebuilt
Classifier: License :: OSI Approved :: BSD License
Classifier: Programming Language :: Python
Classifier: Programming Language :: Python :: 3
Classifier: Programming Language :: Python :: 3.8
Classifier: Programming Language :: Python :: 3.9
Classifier: Programming Language :: Python :: 3.10
Classifier: Programming Language :: Python :: 3.11
Requires-Python: >=3.8
